basyx_client/__init__.py
basyx_client/auth.py
basyx_client/client.py
basyx_client/encoding.py
basyx_client/exceptions.py
basyx_client/pagination.py
basyx_client/serialization.py
basyx_client/cli/__init__.py
basyx_client/cli/config.py
basyx_client/cli/main.py
basyx_client/cli/output.py
basyx_client/cli/commands/__init__.py
basyx_client/cli/commands/aasx.py
basyx_client/cli/commands/concepts.py
basyx_client/cli/commands/discovery.py
basyx_client/cli/commands/elements.py
basyx_client/cli/commands/registry.py
basyx_client/cli/commands/shells.py
basyx_client/cli/commands/submodels.py
basyx_client/endpoints/__init__.py
basyx_client/endpoints/aas_registry.py
basyx_client/endpoints/aas_repository.py
basyx_client/endpoints/aasx_server.py
basyx_client/endpoints/base.py
basyx_client/endpoints/concept_descriptions.py
basyx_client/endpoints/discovery.py
basyx_client/endpoints/submodel_registry.py
basyx_client/endpoints/submodel_repository.py
basyx_client-0.1.4.dist-info/METADATA
basyx_client-0.1.4.dist-info/WHEEL
basyx_client-0.1.4.dist-info/entry_points.txt
basyx_client-0.1.4.dist-info/licenses/LICENSE
basyx_client-0.1.4.dist-info/RECORD
