Metadata-Version: 2.4
Name: basyx-client
Version: 0.1.4
Summary: High-level HTTP client for the AAS Part 2 API v3.x
Project-URL: Homepage, https://github.com/hadijannat/basyx-client
Project-URL: Documentation, https://github.com/hadijannat/basyx-client#readme
Project-URL: Repository, https://github.com/hadijannat/basyx-client
Project-URL: Changelog, https://github.com/hadijannat/basyx-client/blob/main/CHANGELOG.md
Project-URL: Issues, https://github.com/hadijannat/basyx-client/issues
Author: BaSyx Community
License-Expression: Apache-2.0
License-File: LICENSE
Keywords: aas,asset-administration-shell,basyx,digital-twin,industry4.0
Classifier: Development Status :: 3 - Alpha
Classifier: Framework :: AsyncIO
Classifier: Intended Audience :: Developers
Classifier: Intended Audience :: Manufacturing
Classifier: Intended Audience :: Science/Research
Classifier: License :: OSI Approved :: Apache Software License
Classifier: Operating System :: OS Independent
Classifier: Programming Language :: Python :: 3
Classifier: Programming Language :: Python :: 3.10
Classifier: Programming Language :: Python :: 3.11
Classifier: Programming Language :: Python :: 3.12
Classifier: Topic :: Internet :: WWW/HTTP :: HTTP Servers
Classifier: Topic :: Scientific/Engineering
Classifier: Topic :: Software Development :: Libraries :: Python Modules
Classifier: Typing :: Typed
Requires-Python: >=3.10
Requires-Dist: basyx-python-sdk>=2.0.0
Requires-Dist: httpx>=0.27
Provides-Extra: all
Requires-Dist: authlib>=1.3; extra == 'all'
Requires-Dist: mkdocs-material>=9.0; extra == 'all'
Requires-Dist: mkdocs>=1.5; extra == 'all'
Requires-Dist: mkdocstrings[python]>=0.24; extra == 'all'
Requires-Dist: pyyaml>=6.0; extra == 'all'
Requires-Dist: rich>=13.0; extra == 'all'
Requires-Dist: typer>=0.9; extra == 'all'
Provides-Extra: cli
Requires-Dist: pyyaml>=6.0; extra == 'cli'
Requires-Dist: rich>=13.0; extra == 'cli'
Requires-Dist: typer>=0.9; extra == 'cli'
Provides-Extra: dev
Requires-Dist: mypy>=1.10; extra == 'dev'
Requires-Dist: pytest-asyncio>=0.23; extra == 'dev'
Requires-Dist: pytest-httpx>=0.30; extra == 'dev'
Requires-Dist: pytest>=8.0; extra == 'dev'
Requires-Dist: pyyaml>=6.0; extra == 'dev'
Requires-Dist: rich>=13.0; extra == 'dev'
Requires-Dist: ruff>=0.4; extra == 'dev'
Requires-Dist: typer>=0.9; extra == 'dev'
Requires-Dist: types-pyyaml>=6.0.12.20241230; extra == 'dev'
Provides-Extra: docs
Requires-Dist: mkdocs-material>=9.0; extra == 'docs'
Requires-Dist: mkdocs>=1.5; extra == 'docs'
Requires-Dist: mkdocstrings[python]>=0.24; extra == 'docs'
Provides-Extra: oauth
Requires-Dist: authlib>=1.3; extra == 'oauth'
